<?xml version="1.0" encoding="utf-8" ?>
<dwsync>
<file name="loading.gif" local="128247018560000000" remote="0" testing="128247014780000000" />
<file name="invalid_line.gif" local="128247018560000000" remote="0" testing="128247014780000000" />
<file name="mso-hd.gif" local="128247018560000000" remote="0" testing="128247014780000000" />
<file name="grid-blue-split.gif" local="128247018560000000" remote="0" testing="128247014780000000" />
<file name="page-first.gif" local="128247018560000000" remote="0" testing="128247014780000000" />
<file name="done.gif" local="128247018560000000" remote="0" testing="128247014780000000" />
<file name="page-last.gif" local="128247018560000000" remote="0" testing="128247014780000000" />
<file name="page-next.gif" local="128247018560000000" remote="0" testing="128247014780000000" />
<file name="page-prev.gif" local="128247018560000000" remote="0" testing="128247014780000000" />
<file name="page-first-disabled.gif" local="128247018560000000" remote="0" testing="128247014780000000" />
<file name="page-last-disabled.gif" local="128247018560000000" remote="0" testing="128247014780000000" />
<file name="page-next-disabled.gif" local="128247018560000000" remote="0" testing="128247014780000000" />
<file name="page-prev-disabled.gif" local="128247018560000000" remote="0" testing="128247014780000000" />
<file name="row-over.gif" local="128247018560000000" remote="0" testing="128247014780000000" />
<file name="grid3-hrow.gif" local="128290489260000000" remote="0" testing="128290488440000000" />
<file name="hd-pop.gif" local="128247018560000000" remote="0" testing="128247014780000000" />
<file name="grid3-hrow-over.gif" local="128247018560000000" remote="0" testing="128247014780000000" />
<file name="sort_asc.gif" local="128247018600000000" remote="0" testing="128247014780000000" />
<file name="sort_desc.gif" local="128247018600000000" remote="0" testing="128247014780000000" />
<file name="grid-split.gif" local="128247018560000000" remote="0" testing="128247014780000000" />
<file name="col-move-top.gif" local="128247018560000000" remote="0" testing="128247014780000000" />
<file name="col-move-bottom.gif" local="128247018560000000" remote="0" testing="128247014780000000" />
<file name="grid-hrow.gif" local="128247018560000000" remote="0" testing="128247014780000000" />
<file name="dirty.gif" local="128247018560000000" remote="0" testing="128247014780000000" />
<file name="grid3-special-col-bg.gif" local="128247018560000000" remote="0" testing="128247014780000000" />
<file name="hmenu-asc.gif" local="128247018560000000" remote="0" testing="128247014780000000" />
<file name="hmenu-desc.gif" local="128247018560000000" remote="0" testing="128247014780000000" />
<file name="hmenu-lock.gif" local="128247018560000000" remote="0" testing="128247014780000000" />
<file name="hmenu-unlock.gif" local="128247018560000000" remote="0" testing="128247014780000000" />
<file name="grid3-hd-btn.gif" local="128247018560000000" remote="0" testing="128247014780000000" />
<file name="row-expand-sprite.gif" local="128266423960000000" remote="0" testing="128266423740000000" />
<file name="row-check-sprite.gif" local="128247018560000000" remote="0" testing="128247014780000000" />
<file name="grid3-special-col-sel-bg.gif" local="128247018560000000" remote="0" testing="128247014780000000" />
<file name="group-expand-sprite.gif" local="128266424520000000" remote="0" testing="128266423740000000" />
<file name="group-by.gif" local="128275181980000000" remote="0" testing="128275181180000000" />
<file name="columns.gif" local="128266628760000000" remote="0" testing="128266625600000000" />
</dwsync>